chcko-1.3.2-py3.8-nspkg.pth
chcko/google509fdbaf2f77476f.html
chcko/token.pickle
chcko/chcko/__init__.py
chcko/chcko/app.py
chcko/chcko/auth.py
chcko/chcko/bottle.py
chcko/chcko/chelper.html
chcko/chcko/conf.py
chcko/chcko/db.py
chcko/chcko/doit_tasks.py
chcko/chcko/dos.yaml
chcko/chcko/hlp.py
chcko/chcko/inl.py
chcko/chcko/languages.py
chcko/chcko/ndb.py
chcko/chcko/page.html
chcko/chcko/run.py
chcko/chcko/sql.py
chcko/chcko/util.py
chcko/chcko/version.py
chcko/chcko/contents/__init__.py
chcko/chcko/contents/de.html
chcko/chcko/contents/en.html
chcko/chcko/contents/x_.html
chcko/chcko/done/__init__.py
chcko/chcko/done/de.html
chcko/chcko/done/en.html
chcko/chcko/done/x_.html
chcko/chcko/forgot/__init__.py
chcko/chcko/forgot/de.html
chcko/chcko/forgot/de.py
chcko/chcko/forgot/en.html
chcko/chcko/forgot/en.py
chcko/chcko/forgot/x_.html
chcko/chcko/login/__init__.py
chcko/chcko/login/de.html
chcko/chcko/login/en.html
chcko/chcko/login/x_.html
chcko/chcko/main/de.html
chcko/chcko/main/en.html
chcko/chcko/main/x_.html
chcko/chcko/message/__init__.py
chcko/chcko/message/de.html
chcko/chcko/message/en.html
chcko/chcko/org/__init__.py
chcko/chcko/org/de.html
chcko/chcko/org/en.html
chcko/chcko/org/x_.html
chcko/chcko/password/__init__.py
chcko/chcko/password/de.html
chcko/chcko/password/en.html
chcko/chcko/password/x_.html
chcko/chcko/signup/__init__.py
chcko/chcko/signup/de.html
chcko/chcko/signup/de.py
chcko/chcko/signup/en.html
chcko/chcko/signup/en.py
chcko/chcko/signup/x_.html
chcko/chcko/static/960.css
chcko/chcko/static/favicon.ico
chcko/chcko/static/graph.js
chcko/chcko/static/main.css
chcko/chcko/static/pygments.css
chcko/chcko/static/reset.css
chcko/chcko/tests/boddle.py
chcko/chcko/tests/test_content.py
chcko/chcko/tests/test_db.py
chcko/chcko/tests/test_functional.py
chcko/chcko/tests/layout/en.html
chcko/chcko/tests/scripts/script.html
chcko/chcko/tests/t_1/__init__.py
chcko/chcko/tests/t_1/en.html
chcko/chcko/tests/t_2/__init__.py
chcko-1.3.2.dist-info/LICENSE
chcko-1.3.2.dist-info/METADATA
chcko-1.3.2.dist-info/WHEEL
chcko-1.3.2.dist-info/entry_points.txt
chcko-1.3.2.dist-info/namespace_packages.txt
chcko-1.3.2.dist-info/top_level.txt
chcko-1.3.2.dist-info/RECORD
