Metadata-Version: 2.1
Name: chcko
Version: 1.3.2
Summary: chcko randomly parameterized exercises automatically checked (formerly mamchecker)
Home-page: https://github.com/chcko/chcko
Author: Roland Puntaier
Author-email: roland.puntaier@gmail.com
License: UNKNOWN
Platform: UNKNOWN
Classifier: Development Status :: 4 - Beta
Classifier: Intended Audience :: Developers
Classifier: Programming Language :: Python
Classifier: Programming Language :: Python :: 3
Classifier: Programming Language :: Python :: 3.7
Classifier: Programming Language :: Python :: 3.8
Classifier: Operating System :: OS Independent
Classifier: Topic :: Internet
Classifier: License :: OSI Approved :: GNU General Public License (GPL)
Classifier: Topic :: Education
Classifier: Topic :: Education :: Computer Aided Instruction (CAI)
Requires-Dist: numpy
Requires-Dist: matplotlib
Requires-Dist: scipy
Requires-Dist: sympy
Requires-Dist: lxml
Requires-Dist: txdir
Requires-Dist: psutil
